{
  "ai-context": {
    "description": "AI 记忆层 - 用于快速恢复项目上下文",
    "files": [
      {
        "filename": "CONTEXT.md",
        "title": "项目上下文",
        "description": "AI 上下文恢复中枢，30秒了解项目全貌"
      },
      {
        "filename": "CURRENT.md",
        "title": "当前进度",
        "description": "滚动开发日志，记录本周/本月进度"
      }
    ]
  },
  "business": {
    "description": "业务文档 - YBP/YDC 系统需求沟通记录",
    "categories": {
      "overview": {
        "title": "概述",
        "description": "项目背景、术语概念",
        "files": [
          {
            "id": "00",
            "filename": "00_项目概述.md",
            "title": "项目概述",
            "tags": ["项目背景", "YBP", "YDC", "公司介绍"],
            "summary": "项目背景、参与方介绍、系统定位与目标"
          },
          {
            "id": "01",
            "filename": "01_术语与概念.md",
            "title": "术语与概念",
            "tags": ["术语", "概念", "Revit", "BIM"],
            "summary": "BIM/Revit 核心术语、系统核心术语、概念关系梳理"
          }
        ]
      },
      "core-logic": {
        "title": "核心逻辑",
        "description": "清单匹配、工程量计算、参数体系",
        "files": [
          {
            "id": "02",
            "filename": "02_清单匹配逻辑.md",
            "title": "清单匹配逻辑",
            "tags": ["核心功能", "匹配规则", "清单"],
            "summary": "从简单匹配到复杂匹配的演进、匹配条件配置、执行流程"
          },
          {
            "id": "03",
            "filename": "03_工程量计算.md",
            "title": "工程量计算",
            "tags": ["核心功能", "工程量", "计算规则"],
            "summary": "计数、参数汇总、带系数计算等工程量计算方式"
          },
          {
            "id": "04",
            "filename": "04_参数体系.md",
            "title": "参数体系",
            "tags": ["参数", "几何参数", "非几何参数"],
            "summary": "参数分类、几何参数与非几何参数处理、参数同步机制"
          }
        ]
      },
      "implementation": {
        "title": "实现细节",
        "description": "族类型处理、系统原型、场景案例",
        "files": [
          {
            "id": "05",
            "filename": "05_族类型处理.md",
            "title": "族类型处理",
            "tags": ["族", "自建族", "系统族", "叠层墙"],
            "summary": "自建族、系统族、叠层墙的不同处理方式"
          },
          {
            "id": "06",
            "filename": "06_YBP系统原型.md",
            "title": "YBP系统原型",
            "tags": ["原型设计", "架构", "工作流程"],
            "summary": "系统架构、品目管理、清单匹配配置、完整工作流程"
          },
          {
            "id": "07",
            "filename": "07_场景案例.md",
            "title": "场景案例",
            "tags": ["案例", "新风机", "排风扇", "百叶", "楼板"],
            "summary": "新风机、排风扇、MCD新风机、百叶、楼板、叠层墙等具体案例"
          }
        ]
      },
      "pending": {
        "title": "待讨论",
        "description": "尚未解决的问题",
        "files": [
          {
            "id": "99",
            "filename": "99_待讨论问题.md",
            "title": "待讨论问题",
            "tags": ["待讨论", "幕墙", "工程量"],
            "summary": "幕墙工程量、工程量定制、参数同步、权限角色等待讨论问题"
          }
        ]
      }
    }
  },
  "guides": {
    "description": "通用指南 - AI 协作系统配置方法",
    "files": [
      {
        "filename": "01-AI协作系统配置指南.md",
        "title": "AI 协作系统配置指南",
        "description": "完整指南：从零到一建立高效的 AI 协作文档系统与工作流"
      },
      {
        "filename": "02-Slash-Commands完整配置.md",
        "title": "Slash Commands 配置指南",
        "description": "6 个 Slash Commands 的完整配置和使用方法"
      },
      {
        "filename": "03-系统健康排查指南.md",
        "title": "系统健康排查指南",
        "description": "系统健康检查、问题排查、优化建议"
      }
    ]
  }
}
